[{"timestamp":1602296249499,"files":[{"filename":"bundle.*****.esm.js","previous":8658,"size":8659,"diff":1},{"filename":"polyfills.*****.esm.js","previous":2015,"size":2015,"diff":0},{"filename":"route-home.chunk.*****.esm.js","previous":170150,"size":170231,"diff":81},{"filename":"sw-esm.js","previous":8474,"size":8474,"diff":0},{"filename":"sw.js","previous":8471,"size":8471,"diff":0},{"filename":"route-about.chunk.*****.esm.js","previous":719,"size":719,"diff":0},{"filename":"polyfills.694cb.js","previous":2013,"size":2013,"diff":0},{"filename":"route-about.chunk.5a6de.css","previous":175,"size":175,"diff":0},{"filename":"route-home.chunk.cecd7.css","previous":485,"size":0,"diff":-485},{"filename":"route-about.chunk.d4365.js","previous":716,"size":716,"diff":0},{"filename":"bundle.37166.css","previous":818,"size":818,"diff":0},{"filename":"bundle.84a39.js","previous":8609,"size":0,"diff":-8609},{"filename":"route-home.chunk.cbabf.js","previous":174319,"size":0,"diff":-174319},{"filename":"route-home.chunk.04c07.css","previous":0,"size":489,"diff":489},{"filename":"bundle.bf5ea.js","previous":0,"size":8610,"diff":8610},{"filename":"route-home.chunk.7109f.js","previous":0,"size":174405,"diff":174405}]},{"timestamp":1602135220072,"files":[{"filename":"bundle.*****.esm.js","previous":8657,"size":8658,"diff":1},{"filename":"polyfills.*****.esm.js","previous":2015,"size":2015,"diff":0},{"filename":"route-home.chunk.*****.esm.js","previous":170134,"size":170150,"diff":16},{"filename":"sw-esm.js","previous":8474,"size":8474,"diff":0},{"filename":"sw.js","previous":8471,"size":8471,"diff":0},{"filename":"route-about.chunk.*****.esm.js","previous":719,"size":719,"diff":0},{"filename":"polyfills.694cb.js","previous":2013,"size":2013,"diff":0},{"filename":"route-about.chunk.5a6de.css","previous":175,"size":175,"diff":0},{"filename":"route-home.chunk.cecd7.css","previous":485,"size":485,"diff":0},{"filename":"route-home.chunk.72e66.js","previous":174303,"size":0,"diff":-174303},{"filename":"route-about.chunk.d4365.js","previous":716,"size":716,"diff":0},{"filename":"bundle.37166.css","previous":818,"size":818,"diff":0},{"filename":"bundle.3f541.js","previous":8611,"size":0,"diff":-8611},{"filename":"bundle.84a39.js","previous":0,"size":8609,"diff":8609},{"filename":"route-home.chunk.cbabf.js","previous":0,"size":174319,"diff":174319}]},{"timestamp":1601870143879,"files":[{"filename":"bundle.*****.esm.js","previous":8552,"size":8657,"diff":105},{"filename":"polyfills.*****.esm.js","previous":2015,"size":2015,"diff":0},{"filename":"route-home.chunk.*****.esm.js","previous":170134,"size":170134,"diff":0},{"filename":"sw-esm.js","previous":8474,"size":8474,"diff":0},{"filename":"sw.js","previous":8471,"size":8471,"diff":0},{"filename":"route-about.chunk.*****.esm.js","previous":719,"size":719,"diff":0},{"filename":"polyfills.694cb.js","previous":2013,"size":2013,"diff":0},{"filename":"bundle.a22cf.css","previous":711,"size":0,"diff":-711},{"filename":"route-about.chunk.5a6de.css","previous":175,"size":175,"diff":0},{"filename":"route-home.chunk.cecd7.css","previous":485,"size":485,"diff":0},{"filename":"route-home.chunk.72e66.js","previous":174303,"size":174303,"diff":0},{"filename":"bundle.63a13.js","previous":8512,"size":0,"diff":-8512},{"filename":"route-about.chunk.d4365.js","previous":716,"size":716,"diff":0},{"filename":"bundle.37166.css","previous":0,"size":818,"diff":818},{"filename":"bundle.3f541.js","previous":0,"size":8611,"diff":8611}]},{"timestamp":1601784985908,"files":[{"filename":"bundle.*****.esm.js","previous":8552,"size":8552,"diff":0},{"filename":"polyfills.*****.esm.js","previous":2015,"size":2015,"diff":0},{"filename":"route-home.chunk.*****.esm.js","previous":170134,"size":170134,"diff":0},{"filename":"sw-esm.js","previous":8474,"size":8474,"diff":0},{"filename":"sw.js","previous":8471,"size":8471,"diff":0},{"filename":"route-about.chunk.*****.esm.js","previous":624,"size":719,"diff":95},{"filename":"polyfills.694cb.js","previous":2013,"size":2013,"diff":0},{"filename":"bundle.a22cf.css","previous":711,"size":711,"diff":0},{"filename":"route-about.chunk.5a6de.css","previous":175,"size":175,"diff":0},{"filename":"route-home.chunk.cecd7.css","previous":485,"size":485,"diff":0},{"filename":"bundle.9257d.js","previous":8512,"size":0,"diff":-8512},{"filename":"route-about.chunk.a1346.js","previous":628,"size":0,"diff":-628},{"filename":"route-home.chunk.72e66.js","previous":174303,"size":174303,"diff":0},{"filename":"bundle.63a13.js","previous":0,"size":8512,"diff":8512},{"filename":"route-about.chunk.d4365.js","previous":0,"size":716,"diff":716}]},{"timestamp":1601783910458,"files":[{"filename":"bundle.*****.esm.js","previous":8290,"size":8552,"diff":262},{"filename":"polyfills.*****.esm.js","previous":2015,"size":2015,"diff":0},{"filename":"route-home.chunk.*****.esm.js","previous":169949,"size":170134,"diff":185},{"filename":"sw-esm.js","previous":8474,"size":8474,"diff":0},{"filename":"sw.js","previous":8471,"size":8471,"diff":0},{"filename":"bundle.be3de.css","previous":581,"size":0,"diff":-581},{"filename":"route-about.chunk.c526d.css","previous":279,"size":0,"diff":-279},{"filename":"route-about.chunk.*****.esm.js","previous":830,"size":624,"diff":-206},{"filename":"route-home.chunk.7e1ee.css","previous":460,"size":0,"diff":-460},{"filename":"bundle.c032e.js","previous":8254,"size":0,"diff":-8254},{"filename":"polyfills.694cb.js","previous":2013,"size":2013,"diff":0},{"filename":"route-about.chunk.37907.js","previous":817,"size":0,"diff":-817},{"filename":"route-home.chunk.4d9d4.js","previous":174116,"size":0,"diff":-174116},{"filename":"bundle.a22cf.css","previous":0,"size":711,"diff":711},{"filename":"route-about.chunk.5a6de.css","previous":0,"size":175,"diff":175},{"filename":"route-home.chunk.cecd7.css","previous":0,"size":485,"diff":485},{"filename":"bundle.9257d.js","previous":0,"size":8512,"diff":8512},{"filename":"route-about.chunk.a1346.js","previous":0,"size":628,"diff":628},{"filename":"route-home.chunk.72e66.js","previous":0,"size":174303,"diff":174303}]},{"timestamp":1601698715137,"files":[{"filename":"bundle.cc818.css","previous":434,"size":0,"diff":-434},{"filename":"bundle.*****.esm.js","previous":8202,"size":8290,"diff":88},{"filename":"polyfills.*****.esm.js","previous":2011,"size":2015,"diff":4},{"filename":"route-home.chunk.57d0d.css","previous":474,"size":0,"diff":-474},{"filename":"route-home.chunk.*****.esm.js","previous":172633,"size":169949,"diff":-2684},{"filename":"sw-esm.js","previous":8474,"size":8474,"diff":0},{"filename":"sw.js","previous":8471,"size":8471,"diff":0},{"filename":"polyfills.d7424.js","previous":2009,"size":0,"diff":-2009},{"filename":"route-home.chunk.7d0bc.js","previous":176718,"size":0,"diff":-176718},{"filename":"bundle.f4bbd.js","previous":8199,"size":0,"diff":-8199},{"filename":"bundle.be3de.css","previous":0,"size":581,"diff":581},{"filename":"route-about.chunk.c526d.css","previous":0,"size":279,"diff":279},{"filename":"route-about.chunk.*****.esm.js","previous":0,"size":830,"diff":830},{"filename":"route-home.chunk.7e1ee.css","previous":0,"size":460,"diff":460},{"filename":"bundle.c032e.js","previous":0,"size":8254,"diff":8254},{"filename":"polyfills.694cb.js","previous":0,"size":2013,"diff":2013},{"filename":"route-about.chunk.37907.js","previous":0,"size":817,"diff":817},{"filename":"route-home.chunk.4d9d4.js","previous":0,"size":174116,"diff":174116}]},{"timestamp":1601353972301,"files":[{"filename":"bundle.cc818.css","previous":434,"size":434,"diff":0},{"filename":"bundle.*****.esm.js","previous":8245,"size":8202,"diff":-43},{"filename":"polyfills.*****.esm.js","previous":2011,"size":2011,"diff":0},{"filename":"route-home.chunk.57d0d.css","previous":474,"size":474,"diff":0},{"filename":"route-home.chunk.*****.esm.js","previous":172633,"size":172633,"diff":0},{"filename":"sw-esm.js","previous":8474,"size":8474,"diff":0},{"filename":"sw.js","previous":8471,"size":8471,"diff":0},{"filename":"bundle.86265.js","previous":8249,"size":0,"diff":-8249},{"filename":"polyfills.d7424.js","previous":2009,"size":2009,"diff":0},{"filename":"route-home.chunk.7d0bc.js","previous":176718,"size":176718,"diff":0},{"filename":"bundle.f4bbd.js","previous":0,"size":8199,"diff":8199}]},{"timestamp":1601353898134,"files":[{"filename":"ssr-bundle.89d60.css","previous":860,"size":0,"diff":-860},{"filename":"ssr-bundle.js","previous":275266,"size":0,"diff":-275266},{"filename":"bundle.cc818.css","previous":0,"size":434,"diff":434},{"filename":"bundle.*****.esm.js","previous":0,"size":8245,"diff":8245},{"filename":"polyfills.*****.esm.js","previous":0,"size":2011,"diff":2011},{"filename":"route-home.chunk.57d0d.css","previous":0,"size":474,"diff":474},{"filename":"route-home.chunk.*****.esm.js","previous":0,"size":172633,"diff":172633},{"filename":"sw-esm.js","previous":0,"size":8474,"diff":8474},{"filename":"sw.js","previous":0,"size":8471,"diff":8471},{"filename":"bundle.86265.js","previous":0,"size":8249,"diff":8249},{"filename":"polyfills.d7424.js","previous":0,"size":2009,"diff":2009},{"filename":"route-home.chunk.7d0bc.js","previous":0,"size":176718,"diff":176718}]},{"timestamp":1601353862717,"files":[{"filename":"ssr-bundle.89d60.css","previous":0,"size":860,"diff":860},{"filename":"ssr-bundle.js","previous":0,"size":275266,"diff":275266}]}]
